app/__init__.py
app/cli.py
app/cpuset.py
app/nodeset.py
app/output.py
app/system.py
vfio_isolate-0.1.3.dist-info/LICENSE
vfio_isolate-0.1.3.dist-info/METADATA
vfio_isolate-0.1.3.dist-info/WHEEL
vfio_isolate-0.1.3.dist-info/entry_points.txt
vfio_isolate-0.1.3.dist-info/top_level.txt
vfio_isolate-0.1.3.dist-info/RECORD
