Metadata-Version: 2.1
Name: vfio-isolate
Version: 0.1.3
Summary: Commandline tool to facilitate CPU core isolation
Home-page: https://github.com/spheenik/vfio-isolate
Author: Martin Schrodt (spheenik)
Author-email: martin@schrodt.org
License: UNKNOWN
Keywords: vfio cpu isolation
Platform: UNKNOWN
Classifier: Development Status :: 3 - Alpha
Classifier: Intended Audience :: System Administrators
Classifier: Topic :: System :: Systems Administration
Classifier: Operating System :: POSIX :: Linux
Classifier: License :: OSI Approved :: MIT License
Classifier: Programming Language :: Python :: 3.6
Classifier: Programming Language :: Python :: 3.7
Classifier: Programming Language :: Python :: 3.8
Requires-Python: >=3.6, <4
Requires-Dist: click (~=7.1.2)
Requires-Dist: psutil (~=5.7.0)
Requires-Dist: parsimonious (~=0.8.1)
